<?xml version="1.0" encoding="UTF-8"?>
<manual library="API" package="Developer" namespace="\ebuilder\extComponents">
  <class name="extSrcPackage" abstract="" namespace="">
    <info>
      <version/>
      <datecreated>1372693468</datecreated>
      <daterevised>1381483251</daterevised>
      <extends/>
      <implements/>
      <throws/>
      <title>extension Source Package</title>
      <description>Manager source package object in the extension repository.</description>
      <deprecated>Use extension</deprecated>
    </info>
    <constants>
      <const type="integer" name="TEST_CONST">
        <description>a test.</description>
      </const>
    </constants>
    <properties>
      <scope type="public"/>
      <scope type="protected"/>
      <scope type="private">
        <prop type="string" name="testVar">
          <description>a property</description>
        </prop>
      </scope>
    </properties>
    <methods>
      <scope type="public">
        <method name="__construct" returntype="void">
          <description>The contructor</description>
          <parameters>
            <parameter name="$repositoryRoot" type="" defaultvalue="">
              <description/>
            </parameter>
            <parameter name="$srcRepository" type="" defaultvalue="">
              <description/>
            </parameter>
            <parameter name="$releaseFolder" type="" defaultvalue="">
              <description/>
            </parameter>
          </parameters>
          <returndescription/>
          <throws/>
          <deprecated/>
        </method>
        <method name="create" returntype="void">
          <description/>
          <parameters>
            <parameter name="$libName" type="" defaultvalue="">
              <description/>
            </parameter>
            <parameter name="$packageName" type="" defaultvalue="">
              <description/>
            </parameter>
          </parameters>
          <returndescription>The create return value</returndescription>
          <throws/>
          <deprecated/>
        </method>
        <method name="createNS" returntype="boolean">
          <description>Create namespace..</description>
          <parameters>
            <parameter name="$libName" type="string" defaultvalue="">
              <description>Test Desc a string</description>
            </parameter>
            <parameter name="$packageName" type="" defaultvalue="">
              <description/>
            </parameter>
            <parameter name="$nsName" type="" defaultvalue="">
              <description/>
            </parameter>
            <parameter name="$parentNs" type="string" defaultvalue="">
              <description>Test Desc</description>
            </parameter>
          </parameters>
          <returndescription>true or false</returndescription>
          <throws>
            <exception>not</exception>
            <exception>found</exception>
          </throws>
          <deprecated/>
        </method>
        <method name="release" returntype="void">
          <description/>
          <parameters>
            <parameter name="$package" type="" defaultvalue="">
              <description/>
            </parameter>
          </parameters>
          <returndescription/>
          <throws/>
          <deprecated/>
        </method>
      </scope>
      <scope type="protected"/>
      <scope type="private"/>
    </methods>
  </class>
</manual>
